{
    "tituloGeneral": "El Uso de la 'V'",
    "imagenPortada": "/img/personajes/principe/principe.png",
    "lecciones": {
        "1": {
            "titulo": "Formas de vebos",
            "descripcion": "Algunas formas de los verbos estar, andar, tener, mantener, contener y sostener",
            "imagenLeccion": "/img/niveles/lenguaje/vice_viz_vi.png",
            "ejemplos": [
                "Estuviste",
                "Anduvo",
                "Tuvieron",
                "Mantuviese"
            ]
        },
        "2": {
            "titulo": "Después de 'n', 'd' y 'b'",
            "descripcion": "Se escribe 'v' después de las consonantes 'n', 'd' y 'b' en algunas palabras.",
            "imagenLeccion": "/img/niveles/lenguaje/n_d_b.png",
            "ejemplos": [
                "Invitaré a todos mis amigos a la fiesta.",
                "Estuvo de pie delante del grupo."
            ]
        },
        "3": {
            "titulo": "Regla 3: Verbos terminados en '-olver' y sus conjugaciones",
            "descripcion": "Todos los verbos terminados en '-olver' y sus conjugaciones se escriben con 'v'.",
            "imagenLeccion": "/img/niveles/lenguaje/verbos_olver.png",
            "ejemplos": [
                "Él resolvió el problema en cuestión de minutos.",
                "Cuando volvimos a casa, ya era tarde."
            ]
        },
        "4": {
            "titulo": "Palabras que comienzan con:",
            "descripcion": "Las palabras que empiezan con cal-, cer-, cla-, con- y cur-.",
            "imagenLeccion": "/img/niveles/lenguaje/eva_eve_evi_evo.png",
            "ejemplos": [
                "Calvo",
                "Clave",
                "Conversacion",
                "curva"
            ]
        },
        "5": {
            "titulo": "Palabras que empiezan:",
            "descripcion": "Las palabras que empiezan con di-",
            "imagenLeccion": "/img/niveles/lenguaje/voro_vora.png",
            "ejemplos": [
                "Diversidad",
                "Diversión",
                "Divino",
                "Dividir"
            ]
        }
    }
}
