{
    "tituloGeneral": "Los Sustantivos",
    "imagenPortada": "/img/personajes/principe/principe.png",
    "lecciones": {
        "1": {
            "titulo": "Sustantivos: ¿Qué son?",
            "descripcion": "Los sustantivos nombran personas, animales, cosas, lugares o ideas.",
            "imagenLeccion": "/img/niveles/lenguaje/sustantivos.png",
            "ejemplos": [
                "Ejemplo 1: perro, casa, alegría.",
                "Ejemplo 2: niña, ciudad, amor."
            ]
        },
        "2": {
            "titulo": "Sustantivos Comunes y Propios",
            "descripcion": "Comunes nombran de forma general; propios, de manera específica.",
            "imagenLeccion": "/img/niveles/lenguaje/comunes_propios.png",
            "ejemplos": [
                "Ejemplo 1 (común): montaña.",
                "Ejemplo 2 (propio): Monte Everest."
            ]
        },
        "3": {
            "titulo": "Sustantivos Concretos y Abstractos",
            "descripcion": "Concretos se perciben con los sentidos; abstractos, no.",
            "imagenLeccion": "/img/niveles/lenguaje/concretos_abstractos.png",
            "ejemplos": [
                "Ejemplo 1 (concreto): árbol.",
                "Ejemplo 2 (abstracto): felicidad."
            ]
        },
        "4": {
            "titulo": "Sustantivos Individuales y Colectivos",
            "descripcion": "Individuales nombran un solo ser; colectivos, un grupo.",
            "imagenLeccion": "/img/niveles/lenguaje/individuales_colectivos.png",
            "ejemplos": [
                "Ejemplo 1 (individual): abeja.",
                "Ejemplo 2 (colectivo): enjambre."
            ]
        },
        "5": {
            "titulo": "Sustantivos: Género y Número",
            "descripcion": "Los sustantivos pueden ser masculinos o femeninos, singulares o plurales.",
            "imagenLeccion": "/img/niveles/lenguaje/genero_numero.png",
            "ejemplos": [
                "Ejemplo 1 (género): niño (masculino), niña (femenino).",
                "Ejemplo 2 (número): perro (singular), perros (plural)."
            ]
        }
    }
}

