{
    "nombre": "España",
    "gameType": "Seleccionar",
    "imageUrl": "",
    "modalData": {
      "puntaje": "75 estrellas",
      "imagenModal": "",
      "subtitulo": "Explora España",
      "indicaciones": [
        "Selecciona la respuesta correcta sobre España",
        "El puntaje mínimo para pasar es de 60 estrellas",
        "Vuelve a intentarlo si no alcanzas el puntaje mínimo"
      ]
    },
    "totalPuntos": 75,
    "minPuntos": 60,
    "limiteEscenas": 5,
    "escenas": [
      {
        "pregunta": "¿Dónde está ubicada España?",
        "opciones": [
          "Norte de África",
          "Suroeste de Europa",
          "Sudeste de Asia",
          "Oeste de América del Norte"
        ],
        "correcta": "Suroeste de Europa",
        "puntos": 15
      },
      {
        "pregunta": "¿Qué importante acontecimiento consolidó a España como estado moderno en 1492?",
        "opciones": [
          "La Guerra Civil Española",
          "La independencia de España",
          "El descubrimiento de América",
          "La unificación de Castilla y Aragón"
        ],
        "correcta": "La unificación de Castilla y Aragón",
        "puntos": 15
      },
      {
        "pregunta": "¿Cuál es una de las tradiciones culturales más conocidas de España?",
        "opciones": [
          "El hula",
          "El flamenco",
          "El carnaval",
          "El Año Nuevo Chino"
        ],
        "correcta": "El flamenco",
        "puntos": 15
      },
      {
        "pregunta": "¿Qué incluye el escudo de la bandera de España?",
        "opciones": [
          "Símbolos de los antiguos reinos",
          "Una estrella dorada",
          "Un león y un águila",
          "Montañas y ríos"
        ],
        "correcta": "Símbolos de los antiguos reinos",
        "puntos": 15
      },
      {
        "pregunta": "¿Qué cadena montañosa separa a España de Francia?",
        "opciones": [
          "Los Andes",
          "El Himalaya",
          "Los Alpes",
          "Los Pirineos"
        ],
        "correcta": "Los Pirineos",
        "puntos": 15
      }
    ]
  }
  